{
  "IDENTIFIER_TYPE.E55" : "External Identifier Type",
  "INFORMATION_RESOURCE_TYPE_AUTHORITY_DOCUMENT.E32" : null,
  "LANGUAGE_AUTHORITY_DOCUMENT.E32" : null,
  "THUMBNAIL.E62" : "Place Description",
  "DESCRIPTION.E62" : "Description",
  "KEYWORD.E55" : "Keyword",
  "EXTERNAL_XREF_TYPE.E55" : "External Identifier Type",
  "IDENTIFIER_TYPE_AUTHORITY_DOCUMENT.E32" : null,
  "TIME-SPAN_RESOURCE_CREATION_EVENT.E52" : "Time Span of Resource Creation Event",
  "INFORMATION_CARRIER_FORMAT_TYPE.E55" : "Information Carrier Format Type",
  "INFORMATION_RESOURCE.E73" : "Information Resource",
  "INFORMATION_RESOURCE_TYPE.E55" : "Information Resource Type",
  "CREATOR.E39" : "Creator",
  "PUBLISHER_APPELLATION.E82" : "Publisher Appellation",
  "TITLE.E41" : "Title",
  "RIGHT_TYPE.E55" : "Copyright Type",
  "DESCRIPTION_OF_LOCATION.E62" : "Place Description",
  "IDENTIFIER.E42" : "External XRef",
  "CONTRIBUTOR_APPELLATION.E82" : "Contributor Appellation",
  "PLACE.E53" : "Place",
  "GEOMETRY_QUALIFIER_AUTHORITY_DOCUMENT.E32" : null,
  "EXTERNAL_XREF_TYPE_AUTHORITY_DOCUMENT.E32" : null,
  "TITLE_TYPE.E55" : "Title Type",
  "DESCRIPTION_TYPE.E55" : "Description Type",
  "RESOURCE_CREATION_EVENT.E65" : "Resource Creation Event",
  "CREATOR_APPELLATION.E82" : "Creator Appellation",
  "LANGUAGE.E55" : "External Source",
  "EXTERNAL_RESOURCE.E1" : null,
  "GEOMETRY_QUALIFIER.E55" : "Geometry Qualifier",
  "INFORMATION_CARRIER.E84" : "Information Carrier",
  "TIME-SPAN_PUBLICATION_EVENT.E52" : "Time Span Publication Event",
  "TITLE_TYPE_AUTHORITY_DOCUMENT.E32" : null,
  "PUBLICATION_EVENT.E12" : "Publication Event",
  "CONTRIBUTOR.E39" : "Contributor",
  "INFORMATION_RESOURCE_TYPE_ASSIGNMENT.E17" : "Information Resource Type Assignment",
  "RIGHT_TYPE_AUTHORITY_DOCUMENT.E32" : null,
  "DATE_OF_CREATION.E50" : "Date of Creation",
  "SPATIAL_COORDINATES_GEOMETRY.E47" : "Spatial Coordinates Geometry",
  "RIGHT_DESCRIPTION.E30" : "Copyright Description",
  "DATE_OF_PUBLICATION.E50" : "Date of Publication",
  "KEYWORD_AUTHORITY_DOCUMENT.E32" : null,
  "INFORMATION_CARRIER_FORMAT_AUTHORITY_DOCUMENT.E32" : null,
  "PUBLISHER.E39" : "Publisher",
  "DESCRIPTION_TYPE_AUTHORITY_DOCUMENT.E32" : null,
  "DATE_OF_UPDATE.E50" : "Date of Creation",
  "FILE_PATH.E62" : "Information Carrier",
  "RESOURCE_UPDATE_EVENT.E65" : "Resource Creation Event",
  "SPATIAL_COVERAGE.E53" : "Administration Subdivision",
  "EXTERNAL_XREF.E42" : "External XRef",
  "TEMPORAL_COVERAGE.E4" : "Temporal Coverage",
  "TEMPORAL_COVERAGE_TIME-SPAN.E52" : "Temporal Coverage Timespan"
}